MANIFEST.in
README.rst
setup.cfg
setup.py
wenlincms/__init__.py
wenlincms/__init__.pyc
wenlincms/__init__.py~
wenlincms/urls.py
wenlincms.egg-info/PKG-INFO
wenlincms.egg-info/SOURCES.txt
wenlincms.egg-info/dependency_links.txt
wenlincms.egg-info/entry_points.txt
wenlincms.egg-info/not-zip-safe
wenlincms.egg-info/requires.txt
wenlincms.egg-info/top_level.txt
wenlincms/.idea/jsLibraryMappings.xml
wenlincms/.idea/misc.xml
wenlincms/.idea/modules.xml
wenlincms/.idea/wenlincms.iml
wenlincms/.idea/workspace.xml
wenlincms/.idea/inspectionProfiles/Project_Default.xml
wenlincms/.idea/inspectionProfiles/profiles_settings.xml
wenlincms/bin/__init__.py
wenlincms/bin/wenlincms_project.py
wenlincms/boot/__init__.py
wenlincms/boot/lazy_admin.py
wenlincms/boot/models.py
wenlincms/boot/updates/contrib/admin/models.py
wenlincms/boot/updates/contrib/admin/util.py
wenlincms/boot/updates/contrib/admin/widgets.py
wenlincms/boot/updates/contrib/admin/templatetags/admin_list.py
wenlincms/boot/updates/contrib/auth/forms.py
wenlincms/boot/updates/contrib/auth/models.py
wenlincms/boot/updates/contrib/auth/views.py
wenlincms/boot/updates/contrib/auth/locale/zh_CN/LC_MESSAGES/django.mo
wenlincms/boot/updates/contrib/auth/locale/zh_CN/LC_MESSAGES/django.po
wenlincms/boot/updates/contrib/comments/__init__.py
wenlincms/boot/updates/contrib/comments/admin.py
wenlincms/boot/updates/contrib/comments/forms.py
wenlincms/boot/updates/contrib/comments/managers.py
wenlincms/boot/updates/contrib/comments/models.py
wenlincms/boot/updates/contrib/comments/moderation.py
wenlincms/boot/updates/contrib/comments/signals.py
wenlincms/boot/updates/contrib/comments/urls.py
wenlincms/boot/updates/contrib/comments/views/__init__.py
wenlincms/boot/updates/contrib/comments/views/comments.py
wenlincms/boot/updates/contrib/comments/views/moderation.py
wenlincms/boot/updates/contrib/comments/views/utils.py
wenlincms/conf/__init__.py
wenlincms/conf/admin.py
wenlincms/conf/context_processors.py
wenlincms/conf/forms.py
wenlincms/conf/models.py
wenlincms/conf/locale/en/LC_MESSAGES/django.mo
wenlincms/conf/locale/en/LC_MESSAGES/django.po
wenlincms/conf/locale/zh_CN/LC_MESSAGES/django.mo
wenlincms/conf/locale/zh_CN/LC_MESSAGES/django.po
